LICENSE
README.md
setup.py
coregent/__init__.py
coregent/audio.py
coregent/bitmask.py
coregent/frame_group.py
coregent/scancodes.py
coregent/sprite.py
coregent/version.py
coregent.egg-info/PKG-INFO
coregent.egg-info/SOURCES.txt
coregent.egg-info/dependency_links.txt
coregent.egg-info/top_level.txt